{"data":[{"id":"cmms7shru0000g443v7ogr7xt","titleAr":"تطورات الأوضاع الإنسانية في جنوب لبنان","titleEn":"Humanitarian Situation Developments in Southern Lebanon","summaryAr":"تقرير حول الوضع الحالي للنازحين وجهود الإغاثة الجارية في المناطق المتأثرة","sourceName":"الوكالة الوطنية للإعلام","sourceUrl":"https://nna.gov.lb","originalUrl":"https://nna.gov.lb/ar/articles/12345","sourceType":"official","category":"humanitarian","tags":["نازحون","إغاثة","جنوب لبنان"],"imageUrl":null,"coverage":["NNA","LBCI","MTV"],"publishedAt":"2026-03-15T18:36:01.050Z","isBreaking":true,"isVerified":true,"viewCount":0},{"id":"cmms7shzc0001g443ixhatrdr","titleAr":"افتتاح مركز إيواء جديد في ضواحي بيروت","titleEn":"New Shelter Center Opens in Beirut Suburbs","summaryAr":"بلدية بيروت تفتتح مركزاً جديداً يستوعب 500 نازح مع توفير جميع الخدمات الأساسية","sourceName":"LBCI","sourceUrl":"https://lbci.com","originalUrl":"https://lbci.com/news/article/67890","sourceType":"mainstream","category":"shelter","tags":["مركز إيواء","بيروت","بلدية"],"imageUrl":null,"coverage":["LBCI","Future TV","Al Jadeed"],"publishedAt":"2026-03-15T15:36:01.050Z","isBreaking":false,"isVerified":true,"viewCount":0},{"id":"cmms7shzh0002g443pbypg837","titleAr":"تحذير أمني من تحركات في المناطق الحدودية","titleEn":"Security Warning of Movements in Border Areas","summaryAr":"الجيش اللبناني يحذر المدنيين من الاقتراب من المناطق الحدودية الشرقية والجنوبية","sourceName":"الجيش اللبناني","sourceUrl":"https://army.gov.lb","originalUrl":"https://army.gov.lb/statements/2024/03","sourceType":"official","category":"threat","tags":["تحذير","جيش","حدود"],"imageUrl":null,"coverage":["Army","NNA","Reuters"],"publishedAt":"2026-03-15T12:36:01.050Z","isBreaking":true,"isVerified":true,"viewCount":0}],"timestamp":"2026-03-15T21:03:46.600Z","expiresAt":"2026-03-15T21:06:46.600Z","sourceHash":"0865b185d7172dacd8def8e1e10c5db772a0852ab946c33c164198ff309c99f2"}